MANIFEST.in
setup.cfg
setup.py
/usr/local/lib/python3.5/dist-packages/numpy/core/include/numpy/arrayobject.h
/usr/local/lib/python3.5/dist-packages/numpy/core/include/numpy/ufuncobject.h
scikit_garden.egg-info/PKG-INFO
scikit_garden.egg-info/SOURCES.txt
scikit_garden.egg-info/dependency_links.txt
scikit_garden.egg-info/not-zip-safe
scikit_garden.egg-info/requires.txt
scikit_garden.egg-info/top_level.txt
skgarden/__init__.py
skgarden/forest.py
skgarden/setup.py
skgarden/mondrian/__init__.py
skgarden/mondrian/setup.py
skgarden/mondrian/ensemble/__init__.py
skgarden/mondrian/ensemble/forest.py
skgarden/mondrian/ensemble/setup.py
skgarden/mondrian/tree/__init__.py
skgarden/mondrian/tree/_criterion.c
skgarden/mondrian/tree/_criterion.pxd
skgarden/mondrian/tree/_criterion.pyx
skgarden/mondrian/tree/_splitter.c
skgarden/mondrian/tree/_splitter.pxd
skgarden/mondrian/tree/_splitter.pyx
skgarden/mondrian/tree/_tree.c
skgarden/mondrian/tree/_tree.pxd
skgarden/mondrian/tree/_tree.pyx
skgarden/mondrian/tree/_utils.c
skgarden/mondrian/tree/_utils.pxd
skgarden/mondrian/tree/_utils.pyx
skgarden/mondrian/tree/setup.py
skgarden/mondrian/tree/tree.py
skgarden/quantile/__init__.py
skgarden/quantile/ensemble.py
skgarden/quantile/setup.py
skgarden/quantile/tree.py
skgarden/quantile/utils.py