Metadata-Version: 1.1
Name: scikit-garden
Version: 0.1.3
Summary: A garden of scikit-learn compatible trees
Home-page: https://github.com/scikit-garden/scikit-garden
Author: Manoj Kumar
Author-email: mks542@nyu.edu
License: new BSD
Platform: UNKNOWN
Classifier: Intended Audience :: Science/Research
Classifier: Intended Audience :: Developers
Classifier: License :: OSI Approved
Classifier: Programming Language :: C
Classifier: Programming Language :: Python
Classifier: Topic :: Software Development
Classifier: Topic :: Scientific/Engineering
Classifier: Operating System :: Microsoft :: Windows
Classifier: Operating System :: POSIX
Classifier: Operating System :: Unix
Classifier: Operating System :: MacOS
